CHANGES.rst
CONTRIBUTORS.rst
MANIFEST.in
README.rst
setup.cfg
setup.py
docs/LICENSE.GPL
docs/LICENSE.rst
docs/index.rst
src/collective/__init__.py
src/collective.redirector.egg-info/PKG-INFO
src/collective.redirector.egg-info/SOURCES.txt
src/collective.redirector.egg-info/dependency_links.txt
src/collective.redirector.egg-info/entry_points.txt
src/collective.redirector.egg-info/namespace_packages.txt
src/collective.redirector.egg-info/not-zip-safe
src/collective.redirector.egg-info/requires.txt
src/collective.redirector.egg-info/top_level.txt
src/collective/redirector/__init__.py
src/collective/redirector/configure.zcml
src/collective/redirector/interfaces.py
src/collective/redirector/setuphandlers.py
src/collective/redirector/testing.py
src/collective/redirector/browser/__init__.py
src/collective/redirector/browser/configure.zcml
src/collective/redirector/browser/viewlets.py
src/collective/redirector/browser/views.py
src/collective/redirector/browser/overrides/.gitkeep
src/collective/redirector/browser/static/.gitkeep
src/collective/redirector/browser/static/redirector.js
src/collective/redirector/browser/templates/jsfunctions.pt
src/collective/redirector/browser/templates/redirect_page.pt
src/collective/redirector/browser/templates/redirect_viewlet.pt
src/collective/redirector/locales/collective.redirectpage.pot
src/collective/redirector/locales/update.sh
src/collective/redirector/profiles/default/browserlayer.xml
src/collective/redirector/profiles/default/collectiveredirectpage_default.txt
src/collective/redirector/profiles/default/metadata.xml
src/collective/redirector/profiles/default/types.xml
src/collective/redirector/profiles/default/types/RedirectPage.xml
src/collective/redirector/profiles/uninstall/browserlayer.xml
src/collective/redirector/profiles/uninstall/collectiveredirectpage_uninstall.txt
src/collective/redirector/tests/__init__.py
src/collective/redirector/tests/test_redirectpage.py
src/collective/redirector/tests/test_robot.py
src/collective/redirector/tests/test_setup.py
src/collective/redirector/tests/robot/test_example.robot
src/collective/redirector/tests/robot/test_redirectpage.robot