Metadata-Version: 1.1
Name: collective.redirector
Version: 1.0.0
Summary: Allow redirection to a given page based on given url strings that is found on a page.
Home-page: https://pypi.python.org/pypi/collective.redirector
Author: Oshane Bailey
Author-email: b4.oshany@gmail.com
License: GPL version 2
Keywords: Python Plone
Platform: UNKNOWN
Classifier: Environment :: Web Environment
Classifier: Framework :: Plone
Classifier: Framework :: Plone :: 5.0
Classifier: Programming Language :: Python
Classifier: Programming Language :: Python :: 2.7
Classifier: Operating System :: OS Independent
Classifier: License :: OSI Approved :: GNU General Public License v2 (GPLv2)
